forgeo/gdmlib/__init__.py
forgeo/gdmlib/__version__.py
forgeo/gdmlib/distance.py
forgeo/gdmlib/functors.py
forgeo/gdmlib/wrappers.py
forgeo_gdmlib-0.2.post1.dist-info/licenses/LICENSE
forgeo_gdmlib-0.2.post1.dist-info/METADATA
forgeo_gdmlib-0.2.post1.dist-info/WHEEL
forgeo_gdmlib-0.2.post1.dist-info/top_level.txt
forgeo_gdmlib-0.2.post1.dist-info/RECORD
