Metadata-Version: 2.4
Name: forgeo-gdmlib
Version: 0.2.post1
Summary: A forgeo reimplementation of gstlearn functionalities
Author-email: BRGM <forgeo@brgm.fr>
Maintainer-email: BRGM <n.clausolles@brgm.fr>
License:                     GNU AFFERO GENERAL PUBLIC LICENSE
Project-URL: repository, https://gitlab.com/brgm/geomodelling/model/gdmlib
Requires-Python: >=3.10
License-File: LICENSE
Requires-Dist: forgeo>0.6
Requires-Dist: numpy
Requires-Dist: galopy>=0.2.7
Provides-Extra: test
Requires-Dist: pytest; extra == "test"
Dynamic: license-file
